gzusus_image_processing-0.1.dist-info/licenses/LICENSE
image_processing/__init__.py
gzusus_image_processing-0.1.dist-info/METADATA
gzusus_image_processing-0.1.dist-info/WHEEL
gzusus_image_processing-0.1.dist-info/top_level.txt
gzusus_image_processing-0.1.dist-info/RECORD
