Metadata-Version: 2.4
Name: gzusus_image_processing
Version: 0.1
Summary: Pacote simples para processamento de imagens com Python
Home-page: https://github.com/GzuSus/image-processing-package.git
Author: João Vitor
Classifier: Programming Language :: Python :: 3
Classifier: License :: OSI Approved :: MIT License
License-File: LICENSE
Requires-Dist: Pillow
Dynamic: author
Dynamic: classifier
Dynamic: description
Dynamic: description-content-type
Dynamic: home-page
Dynamic: license-file
Dynamic: requires-dist
Dynamic: summary
